pybricks/__init__.py
pybricks/__stub/__control.py
pybricks/__stub/__init__.py
pybricks/ev3devices/__init__.py
pybricks/ev3devices/__stub/__colorsensor.py
pybricks/ev3devices/__stub/__gyrosensor.py
pybricks/ev3devices/__stub/__infraredsensor.py
pybricks/ev3devices/__stub/__init__.py
pybricks/ev3devices/__stub/__motor.py
pybricks/ev3devices/__stub/__touchsensor.py
pybricks/ev3devices/__stub/__ultrasonicsensor.py
pybricks/hubs/__init__.py
pybricks/hubs/__stub/__battery.py
pybricks/hubs/__stub/__buttons.py
pybricks/hubs/__stub/__ev3brick.py
pybricks/hubs/__stub/__init__.py
pybricks/hubs/__stub/__light.py
pybricks/hubs/__stub/__screen.py
pybricks/hubs/__stub/__speaker.py
pybricks/iodevices/__init__.py
pybricks/iodevices/__stub/__analogsensor.py
pybricks/iodevices/__stub/__dcmotor.py
pybricks/iodevices/__stub/__ev3devsensor.py
pybricks/iodevices/__stub/__i2cdevice.py
pybricks/iodevices/__stub/__init__.py
pybricks/iodevices/__stub/__lumpdevice.py
pybricks/iodevices/__stub/__uartdevice.py
pybricks/media/__init__.py
pybricks/media/ev3dev/__init__.py
pybricks/media/ev3dev/__stub/__font.py
pybricks/media/ev3dev/__stub/__image.py
pybricks/media/ev3dev/__stub/__imagefile.py
pybricks/media/ev3dev/__stub/__init__.py
pybricks/media/ev3dev/__stub/__soundfile.py
pybricks/messaging/__init__.py
pybricks/messaging/__stub/__bluetoothmailboxclient.py
pybricks/messaging/__stub/__bluetoothmailboxserver.py
pybricks/messaging/__stub/__init__.py
pybricks/messaging/__stub/__logicmailbox.py
pybricks/messaging/__stub/__mailbox.py
pybricks/messaging/__stub/__numericmailbox.py
pybricks/messaging/__stub/__textmailbox.py
pybricks/nxtdevices/__init__.py
pybricks/nxtdevices/__stub/__colorsensor.py
pybricks/nxtdevices/__stub/__energymeter.py
pybricks/nxtdevices/__stub/__init__.py
pybricks/nxtdevices/__stub/__light.py
pybricks/nxtdevices/__stub/__lightsensor.py
pybricks/nxtdevices/__stub/__soundsensor.py
pybricks/nxtdevices/__stub/__temperaturesensor.py
pybricks/nxtdevices/__stub/__touchsensor.py
pybricks_stubs-2.0.2.dist-info/LICENSE
pybricks_stubs-2.0.2.dist-info/METADATA
pybricks_stubs-2.0.2.dist-info/WHEEL
pybricks_stubs-2.0.2.dist-info/top_level.txt
pybricks_stubs-2.0.2.dist-info/RECORD
