Metadata-Version: 2.1
Name: pybricks-stubs
Version: 2.0.2
Summary: A stubs package to write EV3 Python code.
Home-page: https://github.com/drewwhis/pybricks-stubs
Author: Lawrence (Drew) Whisenant
Author-email: dwhisenant@firstpartners.org
License: UNKNOWN
Platform: UNKNOWN
Classifier: Programming Language :: Python :: 3
Classifier: License :: OSI Approved :: MIT License
Classifier: Operating System :: OS Independent
